Workbook

Sheet TCS_Raw_Data
A1: TCS Income Statement FY25 & FY26
A4: Particulars | B4: FY2025 | C4: FY2026
A5: Revenue from Operations | B5: 214853 | C5: 220938
A6: Other Income | B6: 9642 | C6: 10036
A7: Total Income | B7: 224495 | C7: 230974
A8: Employee Benefit Expenses | B8: 107300 | C8: 112142
A9: Cost of Equipment & Software Licences | B9: 11372 | C9: 3476
A10: Finance Costs | B10: 703 | C10: 1124
A11: Depreciation & Amortisation | B11: 4220 | C11: 4288
A12: Other Expenses | B12: 38252 | C12: 43071
A13: Total Expenses | B13: 161847 | C13: 164101
A14: Profit Before Tax | B14: 62648 | C14: 66873
A15: Tax Expense | B15: 14591 | C15: 13710
A16: Profit for the Year | B16: 48057 | C16: 53163

Sheet TCS_Analysis
A1: TCS Standalone Income Statement Analysis
A2: FY2025 vs FY2026
A5: Revenue & Profitability Analysis
A7: Metric | B7: FY2025 | C7: FY2026 | D7: Change/Growth | E7: Analyst Observation
A8: Revenue from Operations | B8: =TCS_Raw_Data!B5 -> 214853 | C8: =TCS_Raw_Data!C5 -> 220938 | D8: =(C8-B8)/B8 -> 0.02832169 | E8: Revenue increased moderately.
A9: Total Expenses | B9: =TCS_Raw_Data!B13 -> 161847 | C9: =TCS_Raw_Data!C13 -> 164101 | D9: =(C9-B9)/B9 -> 0.013926733 | E9: Expenses grew slower than revenue.
A10: Profit for the Year | B10: =TCS_Raw_Data!B16 -> 48057 | C10: =TCS_Raw_Data!C16 -> 53163 | D10: =(C10-B10)/B10 -> 0.10624883 | E10: Profit grew faster than revenue.
A11: Net Profit Margin | B11: =B10/B8 -> 0.22367386 | C11: =C10/C8 -> 0.24062407 | D11: =C11-B11 -> 0.016950206 | E11: Net profitability improved by approximately 1.70 percentage points.
A13: Expense Analysis
A15: Expense | B15: FY2025 | C15: FY2026 | D15: Growth % | E15: Analyst Observation
A16: Employee Benefit Expenses | B16: =TCS_Raw_Data!B8 -> 107300 | C16: =TCS_Raw_Data!C8 -> 112142 | D16: =(C16-B16)/B16 -> 0.045125815 | E16: Employee costs grew faster than revenue.
A17: Cost of Equipment & Software Licences | B17: =TCS_Raw_Data!B9 -> 11372 | C17: =TCS_Raw_Data!C9 -> 3476 | D17: =(C17-B17)/B17 -> -0.69433697 | E17: Decreased significantly by 69.43%.
A18: Finance Costs | B18: =TCS_Raw_Data!B10 -> 703 | C18: =TCS_Raw_Data!C10 -> 1124 | D18: =(C18-B18)/B18 -> 0.59886202 | E18: Highest percentage increase among major expenses.
A19: Depreciation & Amortisation | B19: =TCS_Raw_Data!B11 -> 4220 | C19: =TCS_Raw_Data!C11 -> 4288 | D19: =(C19-B19)/B19 -> 0.016113744 | E19: Relatively stable.
A20: Other Expenses | B20: =TCS_Raw_Data!B12 -> 38252 | C20: =TCS_Raw_Data!C12 -> 43071 | D20: =(C20-B20)/B20 -> 0.12598034 | E20: Grew significantly faster than revenue.
A21: Total Expenses | B21: =SUM(B16:B20) -> 161847 | C21: =SUM(C16:C20) -> 164101 | D21: =(C21-B21)/B21 -> 0.013926733 | E21: Grew slower than revenue.
A24: Key Analyst Findings
A26: Finding | E26: Observation
A27: Revenue vs Expense Growth | E27: Revenue increased by 2.83%, while total expenses increased by only 1.39%, meaning expenses grew slower than revenue.
A28: Profit Growth | E28: Profit for the year increased by 10.62%, significantly faster than revenue growth of 2.83%.
A29: Net Profit Margin | E29: Net profit margin improved from 22.37% to 24.06%, an improvement of approximately 1.70 percentage points.
A30: Employee Cost Pressure | E30: Employee benefit expenses increased by 4.51%, faster than revenue growth of 2.83%.
A31: Expense Mix | E31: Expense movements were mixed, with equipment/software expenses declining significantly while other expenses and finance costs increased.
