Workbook

Sheet Reliance_Raw_Data
A1: RELIANCE INDUSTRIES INCOME STATEMENT ANALYSIS
A4: Particulars | B4: FY2025 | C4: FY2026
A5: Revenue from Operations | B5: 980136 | C5: 1075675
A6: Other Income | B6: 17978 | C6: 28962
A7: Total Income | B7: 998114 | C7: 1104637
A8: Cost of Materials Consumed | B8: 422127 | C8: 443101
A9: Purchase of Stock-in-Trade | B9: 222686 | C9: 255829
A10: Changes in Inventories | B10: -15124 | C10: -10267
A11: Excise Duty | B11: 15443 | C11: 18456
A12: Employee Benefits Expense | B12: 28559 | C12: 30318
A13: Finance Costs | B13: 24269 | C13: 27061
A14: Depreciation / Amortisation / Depletion | B14: 53136 | C14: 57688
A15: Other Expenses | B15: 141001 | C15: 159289
A16: Total Expenses | B16: 892097 | C16: 981475
... A22: Profit for the Year | B22: 81309 | C22: 95754

Sheet Reliance_Analysis
A1: RELIANCE INDUSTRIES — INCOME STATEMENT ANALYSIS
A2: FY2025 vs FY2026
A5: Revenue & Profitability Analysis
A7: Metric | B7: FY2025 | C7: FY2026 | D7: Change/Growth | E7: Analyst Observation
A8: Revenue from Operations | B8: =Reliance_Raw_Data!B5 -> 980136 | C8: =Reliance_Raw_Data!C5 -> 1075675 | D8: =(C8-B8)/B8 -> 0.097475248 | E8: Revenue increased by 9.75%.
A9: Total Income | B9: =Reliance_Raw_Data!B7 -> 998114 | C9: =Reliance_Raw_Data!C7 -> 1104637 | D9: =(C9-B9)/B9 -> 0.10672428 | E9: Total income increased by 10.67%, slightly faster than revenue.
A10: Total Expenses | B10: =Reliance_Raw_Data!B16 -> 892097 | C10: =Reliance_Raw_Data!C16 -> 981475 | D10: =(C10-B10)/B10 -> 0.10018866 | E10: Total expenses increased by 10.02%, slower than total income.
A11: Profit for the Year | B11: =Reliance_Raw_Data!B22 -> 81309 | C11: =Reliance_Raw_Data!C22 -> 95754 | D11: =(C11-B11)/B11 -> 0.17765561 | E11: Profit for the year increased by 17.77%, faster than total income.
A12: Net Profit Margin | B12: =B11/B8 -> 0.082956855 | C12: =C11/C8 -> 0.089017594 | D12: =C12-B12 -> 0.0060607386 | E12: Net profit margin improved from 8.30% to 8.90%.
A15: Expense Analysis
A17: Metric | B17: FY2025 | C17: FY2026 | D17: Change/Growth | E17: Analyst Observation
A18: Cost of Materials Consumed | B18: =Reliance_Raw_Data!B8 -> 422127 | C18: =Reliance_Raw_Data!C8 -> 443101 | D18: =(C18-B18)/B18 -> 0.049686469 | E18: Cost of materials increased by approximately 4.97%, slower than revenue growth.
A19: Purchase of Stock-in-Trade | B19: =Reliance_Raw_Data!B9 -> 222686 | C19: =Reliance_Raw_Data!C9 -> 255829 | D19: =(C19-B19)/B19 -> 0.14883289 | E19: Purchase of stock-in-trade increased by approximately 14.88%, faster than revenue.
A20: Changes in Inventories | B20: =Reliance_Raw_Data!B10 -> -15124 | C20: =Reliance_Raw_Data!C10 -> -10267 | D20: =(C20-B20)/B20 -> -0.3211452 | E20: Changes in inventories became less negative, indicating a lower inventory adjustment.
A21: Excise Duty | B21: =Reliance_Raw_Data!B11 -> 15443 | C21: =Reliance_Raw_Data!C11 -> 18456 | D21: =(C21-B21)/B21 -> 0.19510458 | E21: Excise duty increased by approximately 19.51%, faster than revenue.
A22: Employee Benefits Expense | B22: =Reliance_Raw_Data!B12 -> 28559 | C22: =Reliance_Raw_Data!C12 -> 30318 | D22: =(C22-B22)/B22 -> 0.061591792 | E22: Employee benefits increased by approximately 6.16%, slower than revenue.
A23: Finance Costs | B23: =Reliance_Raw_Data!B13 -> 24269 | C23: =Reliance_Raw_Data!C13 -> 27061 | D23: =(C23-B23)/B23 -> 0.11504388 | E23: Finance costs increased by approximately 11.51%, faster than revenue.
A24: Depreciation / Amortisation / Depletion | B24: =Reliance_Raw_Data!B14 -> 53136 | C24: =Reliance_Raw_Data!C14 -> 57688 | D24: =(C24-B24)/B24 -> 0.085666968 | E24: Depreciation increased by approximately 8.57%, broadly in line with business growth.
A25: Other Expenses | B25: =Reliance_Raw_Data!B15 -> 141001 | C25: =Reliance_Raw_Data!C15 -> 159289 | D25: =(C25-B25)/B25 -> 0.12970121 | E25: Other expenses increased by approximately 12.97%, faster than revenue.
A26: Total Expenses | B26: =SUM(B18:B25) -> 892097 | C26: =SUM(C18:C25) -> 981475 | D26: =(C26-B26)/B26 -> 0.10018866 | E26: Total expenses increased by 10.02%, slightly slower than total income growth.
A29: Key Analyst Findings
A31: Finding | E31: Observation
A32: Revenue vs Expense Growth | E32: Revenue increased by 9.75%, while total expenses increased by 10.02%, indicating expenses grew slightly faster than revenue.
A33: Profit Growth | E33: Profit for the year increased by 17.77%, significantly faster than revenue growth.
A34: Net Profit Margin | E34: Net profit margin improved from 8.30% to 8.90%, indicating improved profitability.
A35: Expense Pressure | E35: Purchase of stock-in-trade, excise duty, finance costs and other expenses grew faster than revenue.
A36: Cost Structure | E36: Cost movements were mixed, with materials and employee costs growing slower than revenue while several other expense categories grew faster.
